excel_linker/__init__.py
excel_linker/sheet.py
excel_linker/transform.py
excel_linker-0.0.1.dist-info/METADATA
excel_linker-0.0.1.dist-info/WHEEL
excel_linker-0.0.1.dist-info/licenses/LICENSE
excel_linker-0.0.1.dist-info/RECORD
