Metadata-Version: 2.1
Name: excel_linker
Version: 0.0.1
Summary: Excel Linker is used to link excel sheets together.
Project-URL: Homepage, https://github.com/CookieMonsterYan/ExcelLinker
Project-URL: Bug Tracker, https://github.com/CookieMonsterYan/ExcelLinker/issues
Author-email: frozencookie <cookie.monster.yan@hotmail.com>
License:                     GNU GENERAL PUBLIC LICENSE
Classifier: License :: OSI Approved :: GNU General Public License v3 (GPLv3)
Classifier: Operating System :: OS Independent
Classifier: Programming Language :: Python :: 3
Requires-Python: >=3.6
